events/__init__.py
events/admin.py
events/apps.py
events/models.py
events/urls.py
events/views.py
events/events/Dispatcher.py
events/events/Event.py
events/events/Listener.py
events/events/Meta.py
events/events/Observer.py
events/events/__init__.py
events/events/utils.py
events/tests/TestDispatch.py
events/tests/TestDispatcherMock.py
events/tests/TestEvent.py
events/tests/TestUtils.py
events/tests/__init__.py
django_event_system-1.0.1.dist-info/LICENSE
django_event_system-1.0.1.dist-info/METADATA
django_event_system-1.0.1.dist-info/WHEEL
django_event_system-1.0.1.dist-info/top_level.txt
django_event_system-1.0.1.dist-info/RECORD
