Metadata-Version: 2.1
Name: django-event-system
Version: 1.0.1
Summary: A simple package that implements an event system in django
Home-page: http://yoseph.tech/
Author: Yoseph Radding
Author-email: yoseph@shuttl.io
License: MIT
Project-URL: Documentation, https://github.com/radding/django-events/blob/master/README.md
Project-URL: Source, https://github.com/radding/django-events/
Project-URL: Tracker, https://github.com/radding/django-events/issues
Keywords: django events events for django
Platform: UNKNOWN
Classifier: Environment :: Web Environment
Classifier: Framework :: Django
Classifier: Framework :: Django :: 1.7
Classifier: Intended Audience :: Developers
Classifier: License :: OSI Approved :: MIT License
Classifier: Operating System :: OS Independent
Classifier: Programming Language :: Python
Classifier: Programming Language :: Python :: 3.5
Classifier: Programming Language :: Python :: 3.6
Classifier: Topic :: Internet :: WWW/HTTP
Classifier: Topic :: Internet :: WWW/HTTP :: Dynamic Content
Requires-Python: >=3.5
